.gitignore
LICENSE
README.rst
Untitled.ipynb
VERSION
makefile
setup.py
demos/2019-03 Dagstuhl.ipynb
demos/Untitled.ipynb
docs/Makefile
docs/about_TC_morphisms.rst
docs/about_automata.rst
docs/about_folding.rst
docs/about_words.rst
docs/conf.py
docs/finitely_generated_subgroup.rst
docs/index.rst
docs/partial_injections.rst
docs/partial_injections_misc.rst
docs/docsfiles/Makefile
docs/docsfiles/footnotehyper-sphinx.sty
docs/docsfiles/latexmkjarc
docs/docsfiles/latexmkrc
docs/docsfiles/python.ist
docs/docsfiles/sphinx.sty
docs/docsfiles/sphinxhighlight.sty
docs/docsfiles/sphinxhowto.cls
docs/docsfiles/sphinxmanual.cls
docs/docsfiles/sphinxmulticell.sty
docs/docsfiles/stallings_graphs.tex
docs/docsfiles/.doctrees/environment.pickle
docs/docsfiles/.doctrees/index.doctree
stallings_graphs/Untitled1.ipynb
stallings_graphs/__init__.py
stallings_graphs/about_TC_morphisms.py
stallings_graphs/about_automata.py
stallings_graphs/about_bases.py
stallings_graphs/about_folding.py
stallings_graphs/about_free_factors.py
stallings_graphs/about_words.py
stallings_graphs/finitely_generated_subgroup.py
stallings_graphs/partial_injections.py
stallings_graphs/partial_injections_misc.py
stallings_graphs.egg-info/PKG-INFO
stallings_graphs.egg-info/SOURCES.txt
stallings_graphs.egg-info/dependency_links.txt
stallings_graphs.egg-info/requires.txt
stallings_graphs.egg-info/top_level.txt