Metadata-Version: 2.1
Name: stallings-graphs
Version: 0.2
Summary: Stallings graph representation of finitely generated subgroups of free groups
Home-page: https://plmlab.math.cnrs.fr/pascalweil/stallings_graphs
Author: Pascal Weil
Author-email: pascal.weil@cnrs.fr
License: GPLv2+
Keywords: SageMath Stallings Graphs Finitely Generated Subgroups Free Groups
Platform: UNKNOWN
Classifier: Development Status :: 4 - Beta
Classifier: Intended Audience :: Science/Research
Classifier: Topic :: Software Development :: Build Tools
Classifier: Topic :: Scientific/Engineering :: Mathematics
Classifier: License :: OSI Approved :: GNU General Public License v2 or later (GPLv2+)
Classifier: Programming Language :: Python :: 2.7
